golem_garden/__init__.py
golem_garden/__main__.py
golem_garden/backend/__init__.py
golem_garden/backend/golem.py
golem_garden/backend/langchain_stuff/__init__.py
golem_garden/backend/langchain_stuff/agents/__init__.py
golem_garden/backend/langchain_stuff/agents/agent_builder.py
golem_garden/backend/langchain_stuff/agents/get_available_agents.py
golem_garden/backend/langchain_stuff/agents/configuration_tomls/dunkthulu.toml
golem_garden/backend/langchain_stuff/agents/configuration_tomls/golem.toml
golem_garden/backend/langchain_stuff/agents/configuration_tomls/golem_bobolem.toml
golem_garden/backend/langchain_stuff/agents/configuration_tomls/instructions_improver.toml
golem_garden/backend/langchain_stuff/agents/configuration_tomls/midjourney_prompt_builder.toml
golem_garden/backend/langchain_stuff/agents/configuration_tomls/note_taker.toml
golem_garden/backend/langchain_stuff/data_loaders/__init__.py
golem_garden/backend/langchain_stuff/data_loaders/async_load_url_with_playwright.py
golem_garden/backend/langchain_stuff/output_parsers/__init__.py
golem_garden/backend/langchain_stuff/output_parsers/multi_action_output_parser.py
golem_garden/backend/langchain_stuff/prompts/__init__.py
golem_garden/backend/langchain_stuff/prompts/multi_action_prompt_template.py
golem_garden/backend/langchain_stuff/tools/__init__.py
golem_garden/backend/langchain_stuff/tools/directory_printer.py
golem_garden/backend/langchain_stuff/tools/grab_all_py_in_one_text_block.py
golem_garden/backend/langchain_stuff/tools/tools.py
golem_garden/backend/langchain_stuff/tools/output/copy_of_directories_on_2023-04-22_21_26_57_output.md
golem_garden/experimental/__init__.py
golem_garden/experimental/Builder/__init__.py
golem_garden/experimental/Builder/memory_util.py
golem_garden/experimental/Builder/multiplayer_dnd_example.py
golem_garden/experimental/Builder/npc_builder_chain.py
golem_garden/experimental/Builder/agent_definitions/bill_dworld.config
golem_garden-0.6.0.dist-info/entry_points.txt
golem_garden-0.6.0.dist-info/LICENSE
golem_garden-0.6.0.dist-info/WHEEL
golem_garden-0.6.0.dist-info/METADATA
golem_garden-0.6.0.dist-info/RECORD
