Metadata-Version: 2.1
Name: golem_garden
Version: 0.6.0
Summary: Welcome to the Garden - We're so glad you're here <3 
Keywords: chat
Author: Jonathan Samir Matthis
Requires-Python: >=3.8, <4
Classifier: Development Status :: 3 - Alpha
Requires-Dist: python-dotenv
Requires-Dist: toml
Requires-Dist: asyncio
Requires-Dist: fastapi
Requires-Dist: uvicorn
Requires-Dist: rich
Requires-Dist: ipykernel
Requires-Dist: pymongo
Requires-Dist: langchain
Requires-Dist: openai
Requires-Dist: google-search-results
Requires-Dist: wikipedia
Requires-Dist: wolframalpha
Requires-Dist: chromadb
Requires-Dist: pydantic
Requires-Dist: faiss-cpu
Requires-Dist: black ; extra == "dev"
Requires-Dist: bumpver ; extra == "dev"
Requires-Dist: isort ; extra == "dev"
Requires-Dist: pip-tools ; extra == "dev"
Requires-Dist: pytest ; extra == "dev"
Project-URL: Homepage, https://github.com/jonmatthis/golem_garden
Provides-Extra: dev
